BlackBlock/cli.py
BlackBlock/config.py
BlackBlock/last.dat
BlackBlock/requirements.txt
BlackBlock/lib/banner.py
BlackBlock/lib/config.py
BlackBlock/lib/contracts/compile.sh
BlackBlock/modules/block.py
BlackBlock/modules/setup.py
BlackBlock/modules/template.py
BlackBlock/modules/resources/config-sample.py
BlackBlock/modules/resources/config.py
BlackBlock/modules/resources/elk.py
BlackBlock/resources/clean.sh
BlackBlock/resources/genesis.json
BlackBlock/resources/node_start.sh
BlackBlock/resources/stop.sh
BlackBlock-1.0.4.dist-info/LICENSE
BlackBlock-1.0.4.dist-info/METADATA
BlackBlock-1.0.4.dist-info/WHEEL
BlackBlock-1.0.4.dist-info/entry_points.txt
BlackBlock-1.0.4.dist-info/top_level.txt
BlackBlock-1.0.4.dist-info/RECORD
